onionmaker/__init__.py
onionmaker/ed25519.cpython-38-x86_64-linux-gnu.so
onionmaker/__main__.py
onionmaker-0.3.dist-info/LICENSE
onionmaker-0.3.dist-info/entry_points.txt
onionmaker-0.3.dist-info/WHEEL
onionmaker-0.3.dist-info/top_level.txt
onionmaker-0.3.dist-info/RECORD
onionmaker-0.3.dist-info/METADATA
